mri10yr06mo01da_normal
