Metadata-Version: 1.0
Name: mri10yr06mo01da-normal
Version: 1.1.0
Summary: An anonymized MRI exemplar
Home-page: https://github.com/FNNDSC/pl-mri10yr06mo01da_normal
Author: Rudolph Pienaar
Author-email: rudolph.pienaar@gmail.com
License: MIT
Platform: UNKNOWN
